nlppipe/__init__.py
nlppipe/adapter.py
nlppipe/client.py
nlppipe/config.py
nlppipe/server.py
nlppipe-0.1.0.dist-info/LICENSE.txt
nlppipe-0.1.0.dist-info/METADATA
nlppipe-0.1.0.dist-info/WHEEL
nlppipe-0.1.0.dist-info/top_level.txt
nlppipe-0.1.0.dist-info/RECORD
