Metadata-Version: 2.1
Name: nlppipe
Version: 0.1.0
Summary: Latvian NLP Tool Pipeline
Home-page: https://github.com/LUMII-AILab/nlp-pipe
License: gpl-3.0
Keywords: nlp,pipeline,lv
Platform: UNKNOWN
Requires-Dist: kombu
Requires-Dist: flask
Requires-Dist: flask-cors
Requires-Dist: gunicorn
Requires-Dist: python-dotenv
